Rayanoos/__init__.py
Rayanoos/d32_dll_data.py
Rayanoos/d64_dll_data.py
Rayanoos/tools.py
Rayanoos-3.0.2.dist-info/LICENSE
Rayanoos-3.0.2.dist-info/METADATA
Rayanoos-3.0.2.dist-info/WHEEL
Rayanoos-3.0.2.dist-info/top_level.txt
Rayanoos-3.0.2.dist-info/RECORD
