Metadata-Version: 2.1
Name: Rayanoos
Version: 3.0.2
Summary: Special Control System Python Package
Home-page: https://rayanoos.ir
Author: Rayanoos Zareie
Author-email: contact@rayanoos.ir
License: UNKNOWN
Project-URL: Bug Tracker, https://github.com/rayanoos-projects/Rayanoos-Python-Package/issues
Platform: UNKNOWN
Classifier: Programming Language :: Python :: 3
Classifier: License :: OSI Approved :: MIT License
Classifier: Operating System :: OS Independent
Requires-Python: >=3.6
License-File: LICENSE
